LICENSE
README.md
setup.py
xplain/__init__.py
xplain/attribution/__init__.py
xplain/attribution/__main__.py
xplain/attribution/hooks.py
xplain/attribution/model.py
xplain/attribution/postprocessing.py
xplain/attribution/utils.py
xplain/spaceshaping/__init__.py
xplain/spaceshaping/losses_and_evaluators.py
xplain/spaceshaping/model.py
xplain/spaceshaping/util.py
xplain/symbolic/__init__.py
xplain/symbolic/model.py
xplainsim.egg-info/PKG-INFO
xplainsim.egg-info/SOURCES.txt
xplainsim.egg-info/dependency_links.txt
xplainsim.egg-info/requires.txt
xplainsim.egg-info/top_level.txt