Metadata-Version: 2.1
Name: xplainsim
Version: 0.0.1
Summary: A Python package for explaining text similarity
Home-page: https://github.com/flipz357/ExplainSimilarity
Author: Juri Opitz, Andrianos Michail, Lucas Moeller
Author-email: opitz.sci@gmail.com
License: GPLv3
Platform: UNKNOWN
Classifier: License :: OSI Approved :: GNU General Public License v3 (GPLv3)
Requires-Python: >=3.8
License-File: LICENSE
